{
  "NodeType": "Property Resale",
  "GeneratedContexts": [
    "Description",
    "Cashflow"
  ],
  "RelevantContexts": [
    {
      "Type": "Mortgage",
      "SubTypes": [],
      "Ids": [],
      "Filters": null
    },
    {
      "Type": "House",
      "SubTypes": [],
      "Ids": [],
      "Filters": null
    }
  ],
  "RequiredData": [
    {
      "Key": "value",
      "Display": "Value",
      "Type": "float64",
      "Values": [],
      "Example": "Value of Property; eg. 500000",
      "CanModify": false
    }
  ],
  "OptionalData": [],
  "AggregationQueries": [
    {
      "Query": {
        "Type": "Cashflow",
        "SubTypes": [
          "Property Resale"
        ],
        "Ids": [
          "$self"
        ],
        "Filters": {}
      },
      "ContextKey": "value",
      "SaveTo": "value",
      "Collate": false
    }
  ]
}