{
  "8d547f6a-3eb9-4b13-bf24-991da22c7138": {
    "nodeType":      "Me",
    "birthYear":     "1999",
    "birthMonth":    "January",
    "country":       "Canada",
    "state":         "BC",
    "hasDisability": false,
    "startDate":     "2020-01-01",
    "cadence":       "one-time",
    "id":            "8d547f6a-3eb9-4b13-bf24-991da22c7138"
  },  
  "7a4abb8b-0f17-448d-910d-7a0d815b0e8e": {
    "nodeType":     "Modifier",
    "typeToModify": "Income",
    "keyToModify":  "value",
    "idToModify":   "123bjhabsd",
    "action":       "multiply",
    "value":        1.10,
    "startDate":    "2021-04-15",
    "cadence":      "annually",
    "id":           "7a4abb8b-0f17-448d-910d-7a0d815b0e8e"
  },  
  "e7efd2cf-e15a-459a-8d09-0999c74c9d9b": {
    "nodeType":     "Modifier",
    "typeToModify": "Mortgage",
    "idToModify":   "06aea15e-e593-4dfa-ae92-237acff6f1ef",
    "keyToModify":  "",
    "action":       "lumpSumPayments",
    "value":        10000.00,
    "startDate":    "2022-06-06",
    "cadence":      "one-time",
    "id":           "e7efd2cf-e15a-459a-8d09-0999c74c9d9b"
  },
  "bc81fd4d-8e0b-49cb-961c-1ec4b46ee7ba": {
    "nodeType":      "Income",
    "subType":       "EmploymentIncome",
    "value":         5000.00,
    "currency":      "USD",
    "startDate":     "2021-05-05",
    "cadence":       "monthly",
    "id":            "bc81fd4d-8e0b-49cb-961c-1ec4b46ee7ba",
    "inflation":     true,
    "inflationRate": 0.00,
    "owner":         "8d547f6a-3eb9-4b13-bf24-991da22c7138"
  },  
  "4998cd16-369a-481e-8fe0-10f8c594e4dd": {
    "nodeType":  "Expense",
    "value":     600.00,
    "inflation":     true,
    "inflationRate": 0.00,
    "startDate": "2020-01-01",
    "cadence":   "daily",
    "id":        "4998cd16-369a-481e-8fe0-10f8c594e4dd"
  },
  "859ccdaa-14e1-4c73-b985-d1e2596aabcf": {
    "nodeType":         "House",
    "value":            200000.00,
    "startDate":        "2030-01-01",
    "cadence":          "monthly",
    "address":          "1 Centennial Square, Victoria, BC V8W 1N9, Canada",
    "city":             "Victoria",
    "province":         "BC",
    "country":          "Canada",
    "primaryResidence": true,
    "newlyBuilt":       false,
    "inflation":        true,
    "interestRate":     0.02,
    "id":               "859ccdaa-14e1-4c73-b985-d1e2596aabcf"
  },
  "06aea15e-e593-4dfa-ae92-237acff6f1ef": {
    "nodeType":  "Mortgage",
    "cadence":   "monthly",
    "startDate": "2020-01-01",
    "id":        "06aea15e-e593-4dfa-ae92-237acff6f1ef",
    "baseline":  false,
    "isNew":     true,
    "term":      3,  
    "downpaymentData": {
      "lastChangedDownpaymentProperty": "rate",
      "value":                          0.0,
      "downpaymentRate":                20.0
    },  
    "mortgageData": {
      "cadence":            "monthly",
      "rate":               3.25,
      "amortizationPeriod": 10
    }
  },
  "a9a6f72e-f12a-428f-b3cc-2ff7549f5c0c": {
    "nodeType":  "IncomeTax",
    "cadence":   "annually",
    "owner":     "8d547f6a-3eb9-4b13-bf24-991da22c7138",
    "province":  "British Columbia",
    "id":        "a9a6f72e-f12a-428f-b3cc-2ff7549f5c0c",
    "startDate": "2020-01-01"
  },
  "150fccc9-628f-4acb-83d4-046e89c2e1e8": {
    "nodeType":     "Bank Account",
    "balance":      100.00,
    "currency":     "CAD",
    "interestRate": 0.00,
    "startDate":    "2020-01-01",
    "cadence":      "daily",
    "id":           "150fccc9-628f-4acb-83d4-046e89c2e1e8"
  },
  "85cbf4f0-3a3c-4ff1-88e0-defb68de2a05": {
    "nodeType":     "Closing Cost",
    "interestRate": 0.00,
    "id":           "85cbf4f0-3a3c-4ff1-88e0-defb68de2a05",
    "inflation":        true,
    "inflationRate": 0.00,
    "value":      0,
    "cadence":      "one-time",
    "includePropertyEvalFee": true,
    "propertyEvaluationFee": 1000,
    "includeLandSurveyFee": true,
    "landSurveyFee": 200,
    "includeTitleInsurance": false,
    "titleInsurance": 900,
    "includeLegalCosts": true, 
    "legalCosts": 800
  },
  "d5eaa717-63cb-4b6a-ba52-43df42323a70": {
    "nodeType":     "Home Maintenance",
    "cadence":      "monthly",
    "id":           "d5eaa717-63cb-4b6a-ba52-43df42323a70",
    "houseId":      "859ccdaa-14e1-4c73-b985-d1e2596aabcf",
    "inflation":     true,
    "inflationRate": 0.00,
    "value":         0,
    "startDate":    "2020-01-01",
    "budgetList": [
      {
        "title": "Plumbing",
        "value": 40,
        "selected": true,
        "cadence": "monthly"
    },
    {
        "title": "Home Exterior",
        "value": 185,
        "selected": false,
        "cadence": "monthly"
    },
    {
        "title": "Roof",
        "value": 90,
        "selected": true,
        "cadence": "bi-weekly"
    },
    {
        "title": "Foundation",
        "value": 130,
        "selected": true,
        "cadence": "annually"
    },
    {
        "title": "Electrical",
        "value": 40,
        "selected": false,
        "cadence": "monthly"
    },
    {
        "title": "HVAC",
        "value": 55,
        "selected": true,
        "cadence": "monthly"
    },
    {
        "title": "Drainage & Landscaping",
        "value": 50,
        "selected": false,
        "cadence": "monthly"
    }
  ]
  },
  "721fe68c-d8ec-4034-b001-6eef393be8cc": {
    "nodeType": "Real Estate Fees",
    "id": "721fe68c-d8ec-4034-b001-6eef393be8cc",
    "value": 0,
    "cadence": "one-time",
    "resalePrice": 1000000,
    "enteredFeePercent": 5,
    "enteredFeeAmount": 600,
    "lastChangedFeeProperty": "Percent",
    "inflation":     true,
    "inflationRate": 0.00
  }
}
